README.md
muchbettermoments.py
setup.cfg
setup.py
muchbettermoments.egg-info/PKG-INFO
muchbettermoments.egg-info/SOURCES.txt
muchbettermoments.egg-info/dependency_links.txt
muchbettermoments.egg-info/requires.txt
muchbettermoments.egg-info/top_level.txt
muchbettermoments.egg-info/zip-safe